{
    "linux_targets": [
        {
          "arch": "x86_64",
          "target": "ubuntu18.04",
          "type": "deb",
          "platform": "bionic"
        },
        {
          "arch": "x86_64",
          "target": "ubuntu20.04",
          "type": "deb",
          "platform": "focal"
        },
        {
          "arch": "x86_64",
          "target": "ubuntu24.04",
          "type": "deb",
          "platform": "noble"
        },
        {
          "arch": "arm64",
          "target": "ubuntu18.04",
          "type": "deb",
          "platform": "bionic"
        },
        {
          "arch": "arm64",
          "target": "ubuntu20.04",
          "type": "deb",
          "platform": "focal"
        },
        {
          "arch": "arm64",
          "target": "ubuntu24.04",
          "type": "deb",
          "platform": "noble"
        }
      ]
}